[
	{
		"text": "最後の<br/>出会いは<br/>股間にきたよ…<br/>悪い意味でね"
		,"style": "font-size: 14em;left: 9.2482%;top: 3.3398%;width: 13.4845%;height: 10.2263%;border-radius: 50%;font-weight: normal;"
		,"class": "CENTER WHITE"
	}
	,{
		"text": "正直、<br/>苦労するのは<br/>乗り気しないけど<br/>シルキーさんは<br/>俺の心の小ささを<br/>諌めてくれたよ"
		,"style": "font-size: 14em;left: 27.9833%;top: 23.4965%;width: 14.3198%;height: 11.8388%;border-radius: 50%;font-weight: normal;"
		,"class": "CENTER WHITE"
	}
	,{
		"text": "<span class=\"BOLD\">その通り!<br/></span>凶暴さもまた<br/>オシャレよ!"
		,"style": "font-size: 13em;left: 47.0764%;top: 3.5133%;width: 13.2458%;height: 5.8774%;border-radius: 50%;font-weight: normal;"
		,"class": "CENTER WHITE"
	}
	,{
		"text": "あなたを憎むより<br/>己の弱さを嘆き、<br/>重量挙げ部 部長の<br/>ギガントレウスと<br/>ジムの炎で体を<br/>鍛えたわ"
		,"style": "font-size: 14em;left: 46.0024%;top: 9.5587%;width: 16.8258%;height: 13.6020%;border-radius: 40%;font-weight: normal;"
		,"class": "CENTER WHITE"
	}
	,{
		"text": "見返りに、<br/>彼の望む<br/>イメチェン<br/>してあげて<br/>皆ハッピー!"
		,"style": "font-size: 13em;left: 78.2220%;top: 21.7333%;width: 13.1265%;height: 9.4039%;border-radius: 45%;font-weight: normal;"
		,"class": "CENTER WHITE"
	}
	,{
		"text": "えっと…その…<br/>邪魔して悪いけど<br/>始めていいかい?"
		,"style": "font-size: 14em;left: 11.5752%;top: 37.8752%;width: 13.9618%;height: 7.5567%;border-radius: 45%;font-weight: normal;"
		,"class": "CENTER WHITE"
	}
	,{
		"text": "<span class=\"BOLD\">どうぞ!<br/></span>何をすれば<br/>いいの?"
		,"style": "font-size: 14em;left: 38.7828%;top: 39.9743%;width: 12.8878%;height: 5.7095%;border-radius: 45%;font-weight: normal;"
		,"class": "CENTER WHITE"
	}
	,{
		"text": "僕とヒトミ<br/>だけだよ。<br/>君達は<br/>部外者だろ…<br/>ケガするよ"
		,"style": "font-size: 14em;left: 77.6450%;top: 39.1215%;width: 13.7349%;height: 9.5718%;border-radius: 45%;font-weight: normal;"
		,"class": "CENTER WHITE"
	}
	,{
		"text": "私の優雅な<br/>鼻腔に臭うのは<br/>臆病者の悪臭ね?"
		,"style": "font-size: 16em;left: 9.4272%;top: 60.6292%;width: 15.2745%;height: 8.8161%;border-radius: 45%;font-weight: normal;"
		,"class": "CENTER WHITE BOLD"
	}
	,{
		"text": "私達の<br/>体型を見て<br/>怖気付いた<br/>のね?"
		,"style": "font-size: 20em;left: 8.8305%;top: 69.2774%;width: 16.7064%;height: 10.3275%;border-radius: 40%;font-weight: normal;"
		,"class": "CENTER WHITE BOLD"
	}
	,{
		"text": "あの…"
		,"style": "font-size: 12em;left: 37.1122%;top: 62.8962%;width: 5.6086%;height: 3.4425%;border-radius: 45%;font-weight: normal;"
		,"class": "CENTER WHITE"
	}
	,{
		"text": "それか不寛容の<br/>異臭かしら<br/>サイクロプス以外は<br/>祭に参加<br/>するなって?"
		,"style": "font-size: 14em;left: 48.5680%;top: 60.2094%;width: 15.2745%;height: 12.6784%;border-radius: 40%;font-weight: normal;"
		,"class": "CENTER WHITE"
	}
	,{
		"text": "ギガントレウス<br/>私達を<br/>見くびる奴には<br/>何て言う?"
		,"style": "font-size: 14em;left: 82.5776%;top: 62.3924%;width: 13.0072%;height: 9.0680%;border-radius: 40%;font-weight: normal;"
		,"class": "CENTER WHITE"
	}
	,{
		"text": "フンガーーーーーーーーーーーーー!"
		,"style": "font-size: 20em;left: 50.1193%;top: 80.1086%;width: 43.6754%;height: 3.2746%;border-radius: 30%;font-weight: normal;"
		,"class": "CENTER WHITE BOLD"
	}
]